officeboy/__init__.py
officeboy/logging_utils.py
officeboy/sql_utils.py
officeboy/commands/__init__.py
officeboy/connections/__init__.py
officeboy/connections/mqtt_client.py
officeboy/connections/zmq_message_compress.py
officeboy/connections/zmq_pub_sub.py
officeboy/connections/zmq_push_pull.py
officeboy/connections/zmq_qt.py
officeboy/settings/__init__.py
officeboy/settings/log_config.py
officeboy/settings/logging_utils.py
officeboy/settings/test_settings.py
officeboy/settings/yaml_config.py
officeboy/stores/__init__.py
officeboy/stores/model.py
officeboy/stores/sql_helper.py
officeboy/stores/test_sql_helper.py
officeboy/threads/__init__.py
officeboy/threads/simple_thread.py
officeboy-1.0.0.dist-info/DESCRIPTION.rst
officeboy-1.0.0.dist-info/METADATA
officeboy-1.0.0.dist-info/RECORD
officeboy-1.0.0.dist-info/WHEEL
officeboy-1.0.0.dist-info/entry_points.txt
officeboy-1.0.0.dist-info/metadata.json
officeboy-1.0.0.dist-info/top_level.txt
test_officeboy/__init__.py
test_officeboy/test_mqtt_client.py
test_officeboy/test_store_sql_helper.py
test_officeboy/test_zmq_puller.py
test_officeboy/test_zmq_pusher.py
