Metadata-Version: 2.0
Name: officeboy
Version: 1.0.0
Summary: 描述信息
Home-page: UNKNOWN
Author: Peter Jiang
License: UNKNOWN
Platform: UNKNOWN
Requires-Python: >=3.6
